{
    "phone" : {
        "type" : "text",
        "is_where" : false,
        "condition_name" : "phone"
    },

    "commute_type" : {
        "type" : "choose",
        "is_where" : false,
        "list" : [
            {
                "item_name" : "대중교통",
                "condition_name" : "commute_type",
                "condition_value" : "transit"
                
            },
            {
                "item_name" : "자동차",
                "condition_name" : "commute_type",
                "condition_value" : "driving"
            }
        ]
    },

    "commute_time" : {
        "type" : "choose",
        "is_where" : false,
        "list" : [
            {
                "item_name" : "15~30분",
                "condition_name" : "commute_time",
                "condition_value" : {
                    "gte" : 15,
                    "lte" : 30
                }
            },
            {
                "item_name" : "30~60분",
                "condition_name" : "commute_time",
                "condition_value" : {
                    "gte" : 30,
                    "lte" : 60
                }
            },
            {
                "item_name" : "상관없음",
                "condition_name" : "commute_time",
                "condition_value" : {
                    "gte" : 60,
                    "lte" : 9000
                }
            }
        ]
    },

    "commute_location" : {
        "type" : "text",
        "is_where" : false,
        "condition_name" : "commute_location"
    },

    "hobby" : {
        "type" : "choose",
        "is_where" : true,
        "list" : [
            {
                "item_name" : "맛집 탐방",
                "condition_name" : "restaurant",
                "condition_value" : true
            },
            {
                "item_name" : "전시/영화 보기",
                "condition_name" : "cultulral_facility",
                "condition_value" : true
            },
            {
                "item_name" : "집에서 쉬기",
                "condition_name" : "convenience_store",
                "condition_value" : true
            }
        ]
    },

    "deal_type" : {
        "type" : "choose",
        "is_where" : true,
        "list" : [
            {
                "item_name" : "월세",
                "condition_name" : "deal_type",
                "condition_value" : "월세"
            },
            {
                "item_name" : "전세",
                "condition_name" : "deal_type",
                "condition_value" : "전세"
            }
        ]
    },

    "market" : {
        "type" : "choose",
        "is_where" : true,
        "list" : [
            {
                "item_name" : "전통시장",
                "condition_name" : "traditional_market",
                "condition_value" : true
                
            },
            {
                "item_name" : "대형마트",
                "condition_name" : "mart",
                "condition_value" : true
            }
        ]
    },

    "school" : {
        "type" : "choose",
        "is_where" : true,
        "list" : [
            {
                "item_name" : "많았으면",
                "condition_name" : "school",
                "condition_value" : true
            },
            {
                "item_name" : "적었으면",
                "condition_name" : "school",
                "condition_value" : true
            }
        ]
    },

    "build_year" : {
        "type" : "choose",
        "is_where" : true,
        "list" : [
            {
                "item_name" : "새로 지어진 집",
                "condition_name" : "new_building",
                "condition_value" : true
            },
            {
                "item_name" : "오래됐지만 타 조건이 좋은",
                "condition_name" : "new_building",
                "condition_value" : false
            }
        ]
    },

    "subway" : {
        "type" : "choose",
        "is_where" : true,
        "list" : [
            {
                "item_name" : "딱 맞게",
                "condition_name" : "subway",
                "condition_value" : true
            },
            {
                "item_name" : "딱 맞게",
                "condition_name" : "subway",
                "condition_value" : true
            }
        ]
    },

    "deposit" : {
        "type" : "currency",
        "is_where":true,
        "condition_name" : "deposit"
    },

    "monthly_rent" : {
        "type" : "currency",
        "is_where":true,
        "condition_name" : "monthly_rent"
    }
    
}